gitleak/GitLeak.py
gitleak/__init__.py
gitleak/gl_config.py
gitleak-0.9.2.3.dist-info/DESCRIPTION.rst
gitleak-0.9.2.3.dist-info/METADATA
gitleak-0.9.2.3.dist-info/RECORD
gitleak-0.9.2.3.dist-info/WHEEL
gitleak-0.9.2.3.dist-info/metadata.json
gitleak-0.9.2.3.dist-info/top_level.txt
