Metadata-Version: 2.0
Name: gitleak
Version: 0.9.2.3
Summary: A tool library for searching your leaked sourcecode on github
Home-page: https://github.com/lfzark/gitleak
Author: ark1ee
Author-email: lfzlfz@126.com
License: MIT
Keywords: github leak source code
Platform: UNKNOWN
Classifier: Development Status :: 3 - Alpha
Classifier: Intended Audience :: Developers
Classifier: Topic :: Software Development :: Build Tools
Classifier: License :: OSI Approved :: MIT License
Classifier: Programming Language :: Python :: 2
Classifier: Programming Language :: Python :: 2.6
Classifier: Programming Language :: Python :: 2.7
Classifier: Programming Language :: Python :: 3
Classifier: Programming Language :: Python :: 3.2
Classifier: Programming Language :: Python :: 3.3
Classifier: Programming Language :: Python :: 3.4
